{"total":3,"pageSize":10,"pageCount":1,"data":[{"title":"Python爬虫","slug":"Python爬虫","date":"2020-11-12T05:01:19.000Z","updated":"2020-11-12T06:50:53.680Z","comments":true,"path":"api/articles/Python爬虫.json","excerpt":null,"keywords":null,"cover":null,"content":null,"raw":null,"categories":[],"tags":[]},{"title":"指令系统的寻址方式","slug":"singlechip","date":"2020-03-20T23:32:10.000Z","updated":"2020-04-16T02:28:34.000Z","comments":true,"path":"api/articles/singlechip.json","excerpt":null,"keywords":null,"cover":null,"content":null,"raw":null,"categories":[{"name":"learning notes","path":"api/categories/learning notes.json"}],"tags":[{"name":"单片机","path":"api/tags/单片机.json"}]},{"title":"Prevention of new coronavirus","slug":"prevention","date":"2020-03-20T18:16:24.000Z","updated":"2020-04-16T02:28:34.000Z","comments":true,"path":"api/articles/prevention.json","excerpt":null,"keywords":null,"cover":null,"content":null,"raw":null,"categories":[{"name":"life","path":"api/categories/life.json"}],"tags":[{"name":"En notes","path":"api/tags/En notes.json"}]}]}